gtec_licensing/__init__.py
gtec_licensing/__version__.py
gtec_licensing/api.py
gtec_licensing/__pyinstaller/__init__.py
gtec_licensing/__pyinstaller/hook-gtec_licensing.py
gtec_licensing/lib/__init__.py
gtec_licensing/lib/constants.cp311-win_amd64.pyd
gtec_licensing/lib/crypto.cp311-win_amd64.pyd
gtec_licensing/lib/exception.cp311-win_amd64.pyd
gtec_licensing/lib/file_manager.cp311-win_amd64.pyd
gtec_licensing/lib/gtec_licensing_lib.cp311-win_amd64.pyd
gtec_licensing/lib/system.cp311-win_amd64.pyd
gtec_licensing/lib/utilities.cp311-win_amd64.pyd
gtec_licensing/lib/web.cp311-win_amd64.pyd
gtec_licensing/lib/woocommerce_api.cp311-win_amd64.pyd
gtec_licensing-1.0.3.dist-info/licenses/LICENSE-GNCL.txt
gtec_licensing-1.0.3.dist-info/METADATA
gtec_licensing-1.0.3.dist-info/WHEEL
gtec_licensing-1.0.3.dist-info/entry_points.txt
gtec_licensing-1.0.3.dist-info/top_level.txt
gtec_licensing-1.0.3.dist-info/RECORD
