Metadata-Version: 2.4
Name: gtec_licensing
Version: 1.0.3
Summary: g.tec Licensing API
Author-email: "g.tec medical engineering GmbH" <support@gtec.at>
License-Expression: LicenseRef-GNCL
Classifier: Development Status :: 4 - Beta
Classifier: Intended Audience :: Science/Research
Classifier: Intended Audience :: Developers
Classifier: Topic :: Scientific/Engineering
Classifier: Topic :: Software Development :: Libraries :: Python Modules
Classifier: Programming Language :: Python :: 3
Classifier: Programming Language :: Python :: 3.10
Classifier: Programming Language :: Python :: 3.11
Classifier: Programming Language :: Python :: 3.12
Classifier: Programming Language :: Python :: 3.13
Classifier: Operating System :: Microsoft :: Windows
Classifier: Operating System :: MacOS
Requires-Python: >=3.10
License-File: LICENSE-GNCL.txt
Requires-Dist: cryptography>=46.0.3
Requires-Dist: requests>=2.32.5
Provides-Extra: test
Requires-Dist: pytest-cov>=5.0.0; extra == "test"
Requires-Dist: pytest-html>=4.1.1; extra == "test"
Requires-Dist: coverage>=7.6.1; extra == "test"
Requires-Dist: setuptools_scm; extra == "test"
Provides-Extra: build
Requires-Dist: setuptools>=75.3.2; extra == "build"
Requires-Dist: cython>=3.1.1; extra == "build"
Requires-Dist: build>=1.2.2; extra == "build"
Requires-Dist: wheel>=0.45.1; extra == "build"
Requires-Dist: tomli; python_version < "3.11" and extra == "build"
Requires-Dist: setuptools_scm; extra == "build"
Provides-Extra: lint
Requires-Dist: flake8==7.3.0; extra == "lint"
Requires-Dist: black==25.1.0; extra == "lint"
Requires-Dist: isort==6.0.1; extra == "lint"
Provides-Extra: apps
Requires-Dist: pyinstaller; extra == "apps"
Provides-Extra: pypi
Requires-Dist: twine; extra == "pypi"
Provides-Extra: release
Requires-Dist: paramiko; extra == "release"
Requires-Dist: requests; extra == "release"
Dynamic: license-file
